Html5CanvasShizhan/README.md
Html5CanvasShizhan/__init__.py
Html5CanvasShizhan/__main__.py
Html5CanvasShizhan/file.epub
Html5CanvasShizhan/index.html
Html5CanvasShizhan/css/__init__.py
Html5CanvasShizhan/css/annotations.css
Html5CanvasShizhan/css/main.css
Html5CanvasShizhan/css/normalize.css
Html5CanvasShizhan/css/popup.css
Html5CanvasShizhan/font/__init__.py
Html5CanvasShizhan/font/fontello.eot
Html5CanvasShizhan/font/fontello.svg
Html5CanvasShizhan/font/fontello.ttf
Html5CanvasShizhan/font/fontello.woff
Html5CanvasShizhan/img/__init__.py
Html5CanvasShizhan/img/annotator-glyph-sprite.png
Html5CanvasShizhan/img/annotator-icon-sprite.png
Html5CanvasShizhan/img/apple-touch-icon.png
Html5CanvasShizhan/img/cancelfullscreen.png
Html5CanvasShizhan/img/close.png
Html5CanvasShizhan/img/fullscreen.png
Html5CanvasShizhan/img/loader.gif
Html5CanvasShizhan/img/menu-icon.png
Html5CanvasShizhan/img/save.png
Html5CanvasShizhan/img/saved.png
Html5CanvasShizhan/img/settings-s.png
Html5CanvasShizhan/img/settings.png
Html5CanvasShizhan/img/star.png
Html5CanvasShizhan/js/__init__.py
Html5CanvasShizhan/js/epub.js
Html5CanvasShizhan/js/epub.min.js
Html5CanvasShizhan/js/epub.min.map
Html5CanvasShizhan/js/hooks.min.js
Html5CanvasShizhan/js/hooks.min.map
Html5CanvasShizhan/js/reader.js
Html5CanvasShizhan/js/reader.js.map
Html5CanvasShizhan/js/reader.min.js
Html5CanvasShizhan/js/reader.min.map
Html5CanvasShizhan/js/hooks/__init__.py
Html5CanvasShizhan/js/hooks/extensions/__init__.py
Html5CanvasShizhan/js/hooks/extensions/highlight.js
Html5CanvasShizhan/js/libs/__init__.py
Html5CanvasShizhan/js/libs/jquery.min.js
Html5CanvasShizhan/js/libs/localforage.min.js
Html5CanvasShizhan/js/libs/screenfull.js
Html5CanvasShizhan/js/libs/screenfull.min.js
Html5CanvasShizhan/js/libs/zip.min.js
Html5CanvasShizhan/js/plugins/__init__.py
Html5CanvasShizhan/js/plugins/hypothesis.js
Html5CanvasShizhan/js/plugins/search.js
html5_canvas_shizhan-2024.3.4.0.dist-info/METADATA
html5_canvas_shizhan-2024.3.4.0.dist-info/WHEEL
html5_canvas_shizhan-2024.3.4.0.dist-info/entry_points.txt
html5_canvas_shizhan-2024.3.4.0.dist-info/top_level.txt
html5_canvas_shizhan-2024.3.4.0.dist-info/RECORD
